spectra_ez_download/__init__.py
spectra_ez_download/average_spectrum.py
spectra_ez_download/ez_spectral_analysis.py
spectra_ez_download/interpolation.py
spectra_ez_download/tests/test.py
spectra_ez_download/tests/test_unit_angstrom.py
spectra_ez_download/tests/test_upload.py
spectra_ez_download-0.1.4.dist-info/LICENSE.txt
spectra_ez_download-0.1.4.dist-info/METADATA
spectra_ez_download-0.1.4.dist-info/WHEEL
spectra_ez_download-0.1.4.dist-info/top_level.txt
spectra_ez_download-0.1.4.dist-info/RECORD
