Metadata-Version: 2.1
Name: spectra_ez_download
Version: 0.1.4
License-File: LICENSE.txt
Requires-Dist: numpy
Requires-Dist: astropy
Requires-Dist: pandas
Requires-Dist: matplotlib
Requires-Dist: scipy
Requires-Dist: specutils
